lecluvindex.py
lecluvindex-1.1.0b0.dist-info/METADATA
lecluvindex-1.1.0b0.dist-info/RECORD
lecluvindex-1.1.0b0.dist-info/WHEEL
lecluvindex-1.1.0b0.dist-info/entry_points.txt
lecluvindex-1.1.0b0.dist-info/top_level.txt
