Metadata-Version: 2.1
Name: lecluvindex
Version: 1.1.0b0
Summary: Chilean UV index plugin for the Le bot.
Home-page: https://github.com/cganterh/lecluvindex
Author: Cristóbal Ganter
Author-email: cganterh@gmail.com
License: MIT
Keywords: python,python3,telegram-bot,chatbot
Platform: UNKNOWN
Classifier: Environment :: Web Environment
Classifier: Intended Audience :: System Administrators
Classifier: License :: OSI Approved :: MIT License
Classifier: Natural Language :: English
Classifier: Programming Language :: Python :: 3.5
Classifier: Programming Language :: Python :: 3.6
Classifier: Topic :: Communications :: Chat
Requires-Dist: python-telegram-bot (~=10.0)
Requires-Dist: requests (~=2.18)
